pika/__init__.py
pika/amqp_object.py
pika/callback.py
pika/channel.py
pika/compat.py
pika/connection.py
pika/credentials.py
pika/data.py
pika/exceptions.py
pika/frame.py
pika/heartbeat.py
pika/spec.py
pika/tcp_socket_opts.py
pika/adapters/__init__.py
pika/adapters/asyncio_connection.py
pika/adapters/base_connection.py
pika/adapters/blocking_connection.py
pika/adapters/select_connection.py
pika/adapters/tornado_connection.py
pika/adapters/twisted_connection.py
pika_dev-1.0.0b1.dev1.dist-info/DESCRIPTION.rst
pika_dev-1.0.0b1.dev1.dist-info/METADATA
pika_dev-1.0.0b1.dev1.dist-info/RECORD
pika_dev-1.0.0b1.dev1.dist-info/WHEEL
pika_dev-1.0.0b1.dev1.dist-info/metadata.json
pika_dev-1.0.0b1.dev1.dist-info/top_level.txt
pika_dev-1.0.0b1.dev1.dist-info/zip-safe
